{"hierarchy":{"paths":[["doc://com.apple.documentation/documentation/technologies","doc://com.apple.devicemanagement/documentation/DeviceManagement"]]},"schemaVersion":{"major":0,"minor":3,"patch":0},"abstract":[{"text":"The payload that configures the Dock.","type":"text"}],"topicSections":[{"anchor":"Objects","identifiers":["doc://com.apple.devicemanagement/documentation/DeviceManagement/Dock/StaticItem"],"title":"Objects"}],"seeAlsoSections":[{"title":"User experience","generated":true,"anchor":"User-experience","identifiers":["doc://com.apple.devicemanagement/documentation/DeviceManagement/Accessibility","doc://com.apple.devicemanagement/documentation/DeviceManagement/Desktop","doc://com.apple.devicemanagement/documentation/DeviceManagement/Finder","doc://com.apple.devicemanagement/documentation/DeviceManagement/HomeScreenLayout","doc://com.apple.devicemanagement/documentation/DeviceManagement/ManagedMenuExtras","doc://com.apple.devicemanagement/documentation/DeviceManagement/Notifications","doc://com.apple.devicemanagement/documentation/DeviceManagement/ScreensaverUser","doc://com.apple.devicemanagement/documentation/DeviceManagement/SetupAssistant","doc://com.apple.devicemanagement/documentation/DeviceManagement/TimeMachine"]}],"primaryContentSections":[{"declarations":[{"platforms":["macOS"],"tokens":[{"kind":"text","text":"object "},{"kind":"identifier","text":"Dock"}],"languages":["data"]}],"kind":"declarations"},{"items":[{"attributes":[{"value":"false","kind":"default"}],"name":"AllowDockFixupOverride","type":[{"text":"boolean","kind":"text"}],"content":[{"inlineContent":[{"type":"text","text":"If "},{"code":"true","type":"codeVoice"},{"text":", use the file in ","type":"text"},{"type":"codeVoice","code":"/Library/Preferences/com.apple.dockfixup.plist"},{"type":"text","text":" when a new user or migrated user logs in. This option has no effect for existing users. Only available on the device channel."}],"type":"paragraph"},{"type":"paragraph","inlineContent":[{"text":"Available: macOS 10.12+","type":"text"}]}],"required":false,"introducedVersion":"10.7.0"},{"required":false,"introducedVersion":"10.7.0","name":"autohide","type":[{"kind":"text","text":"boolean"}],"attributes":[{"value":"false","kind":"default"}],"content":[{"type":"paragraph","inlineContent":[{"text":"If ","type":"text"},{"type":"codeVoice","code":"true"},{"type":"text","text":", enables “Automatically hide and show the Dock.”"}]}]},{"type":[{"text":"boolean","kind":"text"}],"introducedVersion":"10.7.0","content":[{"type":"paragraph","inlineContent":[{"type":"text","text":"If "},{"type":"codeVoice","code":"true"},{"type":"text","text":", locks “Automatically hide.”"}]}],"name":"autohide-immutable","attributes":[{"value":"false","kind":"default"}],"required":false},{"required":false,"attributes":[{"kind":"default","value":"false"}],"introducedVersion":"10.7.0","name":"contents-immutable","type":[{"text":"boolean","kind":"text"}],"content":[{"inlineContent":[{"type":"text","text":"If "},{"type":"codeVoice","code":"true"},{"text":", disables changes to the Dock.","type":"text"}],"type":"paragraph"}]},{"attributes":[{"kind":"allowedValues","values":["minimize","maximize","none"]}],"required":false,"content":[{"inlineContent":[{"text":"The behavior when the window’s title bar is double-clicked.","type":"text"}],"type":"paragraph"},{"type":"paragraph","inlineContent":[{"text":"Available: macOS 10.15+","type":"text"}]}],"introducedVersion":"10.7.0","name":"dblclickbehavior","type":[{"kind":"text","text":"string"}]},{"type":[{"kind":"text","text":"boolean"}],"required":false,"introducedVersion":"10.7.0","name":"dblclickbehavior-immutable","content":[{"inlineContent":[{"text":"If ","type":"text"},{"code":"true","type":"codeVoice"},{"type":"text","text":", locks “Double-click a window’s title bar.”"}],"type":"paragraph"},{"type":"paragraph","inlineContent":[{"type":"text","text":"Available: macOS 10.14+"}]}],"attributes":[{"value":"false","kind":"default"}]},{"introducedVersion":"10.7.0","name":"largesize","type":[{"kind":"text","text":"integer"}],"attributes":[{"value":"16","kind":"minimum"},{"kind":"maximum","value":"128"}],"required":false,"content":[{"inlineContent":[{"text":"The size of the largest magnification.","type":"text"}],"type":"paragraph"}]},{"required":false,"attributes":[{"value":"false","kind":"default"}],"introducedVersion":"10.7.0","name":"launchanim","type":[{"kind":"text","text":"boolean"}],"content":[{"type":"paragraph","inlineContent":[{"text":"If ","type":"text"},{"type":"codeVoice","code":"true"},{"type":"text","text":", enables “Animate opening applications.”"}]}]},{"type":[{"kind":"text","text":"boolean"}],"content":[{"inlineContent":[{"text":"If ","type":"text"},{"type":"codeVoice","code":"true"},{"type":"text","text":", locks “Animate opening applications.”"}],"type":"paragraph"}],"attributes":[{"kind":"default","value":"false"}],"required":false,"name":"launchanim-immutable","introducedVersion":"10.7.0"},{"introducedVersion":"10.7.0","name":"magnification","attributes":[{"value":"false","kind":"default"}],"type":[{"text":"boolean","kind":"text"}],"content":[{"type":"paragraph","inlineContent":[{"type":"text","text":"If "},{"type":"codeVoice","code":"true"},{"type":"text","text":", enables magnification."}]}],"required":false},{"required":false,"attributes":[{"value":"false","kind":"default"}],"type":[{"text":"boolean","kind":"text"}],"content":[{"type":"paragraph","inlineContent":[{"text":"If ","type":"text"},{"type":"codeVoice","code":"true"},{"text":", locks magnification.","type":"text"}]}],"introducedVersion":"10.7.0","name":"magnify-immutable"},{"required":false,"introducedVersion":"10.7.0","type":[{"kind":"text","text":"boolean"}],"attributes":[{"value":"false","kind":"default"}],"name":"magsize-immutable","content":[{"type":"paragraph","inlineContent":[{"type":"text","text":"If "},{"code":"true","type":"codeVoice"},{"type":"text","text":", locks the magnification slider."}]}]},{"attributes":[{"kind":"allowedValues","values":["AddDockMCXMyApplicationsFolder","AddDockMCXDocumentsFolder","AddDockMCXSharedFolder","AddDockMCXOriginalNetworkHomeFolder"]}],"name":"MCXDockSpecialFolders","type":[{"kind":"text","text":"[string]"}],"content":[{"type":"paragraph","inlineContent":[{"type":"text","text":"One or more special folders that the device may create at user login time and place in the Dock."}]},{"type":"paragraph","inlineContent":[{"text":"The “My Applications” item is only used for Simple Finder environments. The “Original Network Home” item is only used for mobile account users.","type":"text"}]}],"required":false,"introducedVersion":"10.7.0"},{"name":"mineffect","type":[{"text":"string","kind":"text"}],"content":[{"type":"paragraph","inlineContent":[{"text":"The minimize effect.","type":"text"}]}],"attributes":[{"kind":"allowedValues","values":["genie","scale"]}],"required":false,"introducedVersion":"10.7.0"},{"introducedVersion":"10.7.0","name":"mineffect-immutable","type":[{"kind":"text","text":"boolean"}],"content":[{"type":"paragraph","inlineContent":[{"type":"text","text":"If "},{"code":"true","type":"codeVoice"},{"text":", locks “Minimize windows using.”","type":"text"}]}],"attributes":[{"value":"false","kind":"default"}],"required":false},{"required":false,"type":[{"kind":"text","text":"boolean"}],"content":[{"type":"paragraph","inlineContent":[{"type":"text","text":"If "},{"code":"true","type":"codeVoice"},{"type":"text","text":", enables “Minimize windows into application icon.”"}]}],"introducedVersion":"10.7.0","name":"minimize-to-application","attributes":[{"value":"false","kind":"default"}]},{"content":[{"type":"paragraph","inlineContent":[{"text":"If ","type":"text"},{"type":"codeVoice","code":"true"},{"text":", disables the “Minimize windows into application icon” checkbox.","type":"text"}]},{"inlineContent":[{"text":"Available: macOS 10.14+","type":"text"}],"type":"paragraph"}],"required":false,"type":[{"text":"boolean","kind":"text"}],"attributes":[{"kind":"default","value":"false"}],"introducedVersion":"10.7.0","name":"minintoapp-immutable"},{"required":false,"content":[{"inlineContent":[{"text":"The orientation of the Dock.","type":"text"}],"type":"paragraph"}],"name":"orientation","type":[{"kind":"text","text":"string"}],"attributes":[{"kind":"allowedValues","values":["bottom","left","right"]}],"introducedVersion":"10.7.0"},{"attributes":[],"name":"persistent-apps","type":[{"text":"[","kind":"text"},{"preciseIdentifier":"mdm-profiles:Dock.StaticItem","kind":"typeIdentifier","identifier":"doc://com.apple.devicemanagement/documentation/DeviceManagement/Dock/StaticItem","text":"Dock.StaticItem"},{"text":"]","kind":"text"}],"content":[{"type":"paragraph","inlineContent":[{"type":"text","text":"An array of items located on the Applications side of the Dock that users can remove from the Dock."}]}],"introducedVersion":"10.7.0","required":false},{"introducedVersion":"10.7.0","content":[{"inlineContent":[{"text":"An array of items located on the Documents side of the Dock that users can remove from the Dock.","type":"text"}],"type":"paragraph"}],"name":"persistent-others","type":[{"kind":"text","text":"["},{"text":"Dock.StaticItem","preciseIdentifier":"mdm-profiles:Dock.StaticItem","kind":"typeIdentifier","identifier":"doc://com.apple.devicemanagement/documentation/DeviceManagement/Dock/StaticItem"},{"text":"]","kind":"text"}],"attributes":[],"required":false},{"type":[{"text":"boolean","kind":"text"}],"name":"position-immutable","content":[{"type":"paragraph","inlineContent":[{"text":"If ","type":"text"},{"type":"codeVoice","code":"true"},{"type":"text","text":", locks the position."}]}],"attributes":[{"kind":"default","value":"false"}],"required":false,"introducedVersion":"10.7.0"},{"required":false,"introducedVersion":"10.7.0","name":"show-process-indicators","type":[{"kind":"text","text":"boolean"}],"content":[{"type":"paragraph","inlineContent":[{"text":"If true, shows the process indicator.","type":"text"}]}],"attributes":[{"value":"false","kind":"default"}]},{"content":[{"inlineContent":[{"text":"If ","type":"text"},{"code":"true","type":"codeVoice"},{"type":"text","text":", enables “Show recent items.”"}],"type":"paragraph"},{"inlineContent":[{"text":"Available: macOS 10.14+","type":"text"}],"type":"paragraph"}],"type":[{"kind":"text","text":"boolean"}],"required":false,"name":"show-recents","attributes":[{"kind":"default","value":"false"}],"introducedVersion":"10.7.0"},{"attributes":[{"value":"false","kind":"default"}],"required":false,"introducedVersion":"10.7.0","type":[{"kind":"text","text":"boolean"}],"name":"showindicators-immutable","content":[{"type":"paragraph","inlineContent":[{"type":"text","text":"If "},{"type":"codeVoice","code":"true"},{"text":", locks “Show indicators.”","type":"text"}]}]},{"required":false,"name":"showrecents-immutable","introducedVersion":"10.7.0","type":[{"kind":"text","text":"boolean"}],"attributes":[{"value":"false","kind":"default"}],"content":[{"inlineContent":[{"text":"If ","type":"text"},{"type":"codeVoice","code":"true"},{"text":", disables “Show recent applications” checkbox.","type":"text"}],"type":"paragraph"},{"type":"paragraph","inlineContent":[{"text":"Available: macOS 10.15+","type":"text"}]}]},{"introducedVersion":"10.7.0","required":false,"attributes":[{"kind":"default","value":"false"}],"type":[{"text":"boolean","kind":"text"}],"name":"size-immutable","content":[{"type":"paragraph","inlineContent":[{"type":"text","text":"If "},{"code":"true","type":"codeVoice"},{"text":", locks the size slider.","type":"text"}]}]},{"content":[{"type":"paragraph","inlineContent":[{"type":"text","text":"An array of items located on the Applications side of the Dock that users can’t remove from that location."}]}],"type":[{"text":"[","kind":"text"},{"preciseIdentifier":"mdm-profiles:Dock.StaticItem","kind":"typeIdentifier","text":"Dock.StaticItem","identifier":"doc://com.apple.devicemanagement/documentation/DeviceManagement/Dock/StaticItem"},{"kind":"text","text":"]"}],"required":false,"attributes":[],"introducedVersion":"10.7.0","name":"static-apps"},{"attributes":[{"kind":"default","value":"false"}],"name":"static-only","required":false,"introducedVersion":"10.7.0","type":[{"kind":"text","text":"boolean"}],"content":[{"type":"paragraph","inlineContent":[{"text":"If ","type":"text"},{"type":"codeVoice","code":"true"},{"text":", uses the ","type":"text"},{"type":"codeVoice","code":"static-apps"},{"text":" and ","type":"text"},{"code":"static-others","type":"codeVoice"},{"text":" dictionaries for the Dock and ignores any items in the ","type":"text"},{"type":"codeVoice","code":"persistent-apps"},{"text":" and ","type":"text"},{"code":"persistent-others","type":"codeVoice"},{"type":"text","text":" dictionaries. If "},{"type":"codeVoice","code":"false"},{"text":", the contents are merged with the static items listed first.","type":"text"}]}]},{"attributes":[],"type":[{"text":"[","kind":"text"},{"identifier":"doc://com.apple.devicemanagement/documentation/DeviceManagement/Dock/StaticItem","kind":"typeIdentifier","preciseIdentifier":"mdm-profiles:Dock.StaticItem","text":"Dock.StaticItem"},{"text":"]","kind":"text"}],"introducedVersion":"10.7.0","content":[{"inlineContent":[{"type":"text","text":"An array of items located on the Documents side of the Dock that users can’t remove from that location."}],"type":"paragraph"}],"required":false,"name":"static-others"},{"content":[{"inlineContent":[{"text":"The tile size. Values must be in the range from 16 to 128.","type":"text"}],"type":"paragraph"}],"name":"tilesize","required":false,"introducedVersion":"10.7.0","type":[{"kind":"text","text":"integer"}],"attributes":[{"kind":"minimum","value":"16"},{"value":"128","kind":"maximum"}]},{"content":[{"inlineContent":[{"text":"Set the “Prefer tabs when opening documents” to the provided value.","type":"text"}],"type":"paragraph"},{"type":"paragraph","inlineContent":[{"type":"text","text":"Available: macOS 10.15+"}]}],"attributes":[{"kind":"allowedValues","values":["manual","always","fullscreen"]}],"introducedVersion":"10.7.0","name":"windowtabbing","type":[{"kind":"text","text":"string"}],"required":false},{"name":"windowtabbing-immutable","type":[{"kind":"text","text":"boolean"}],"content":[{"inlineContent":[{"text":"If ","type":"text"},{"type":"codeVoice","code":"true"},{"text":", disables “Prefer tabs when opening documents” checkbox.","type":"text"}],"type":"paragraph"},{"inlineContent":[{"type":"text","text":"Available: macOS 10.12+"}],"type":"paragraph"}],"attributes":[{"value":"false","kind":"default"}],"required":false,"introducedVersion":"10.7.0"}],"kind":"properties","title":"Properties"},{"content":[{"type":"heading","level":2,"anchor":"Discussion","text":"Discussion"},{"inlineContent":[{"type":"text","text":"Specify "},{"code":"com.apple.dock","type":"codeVoice"},{"text":" as the payload type.","type":"text"}],"type":"paragraph"},{"level":3,"text":"Profile availability","anchor":"Profile-availability","type":"heading"},{"type":"table","rows":[[[{"type":"paragraph","inlineContent":[]}],[{"type":"paragraph","inlineContent":[]}]],[[{"type":"paragraph","inlineContent":[{"text":"Device channel","type":"text"}]}],[{"inlineContent":[{"text":"macOS","type":"text"}],"type":"paragraph"}]],[[{"type":"paragraph","inlineContent":[{"text":"User channel","type":"text"}]}],[{"type":"paragraph","inlineContent":[{"type":"text","text":"macOS"}]}]],[[{"type":"paragraph","inlineContent":[{"type":"text","text":"Allow manual install"}]}],[{"inlineContent":[{"type":"text","text":"macOS"}],"type":"paragraph"}]],[[{"inlineContent":[{"type":"text","text":"Requires supervision"}],"type":"paragraph"}],[{"type":"paragraph","inlineContent":[{"text":"N/A","type":"text"}]}]],[[{"inlineContent":[{"text":"Requires user-approved MDM","type":"text"}],"type":"paragraph"}],[{"type":"paragraph","inlineContent":[{"type":"text","text":"N/A"}]}]],[[{"inlineContent":[{"text":"Allowed in user enrollment","type":"text"}],"type":"paragraph"}],[{"type":"paragraph","inlineContent":[{"text":"N/A","type":"text"}]}]],[[{"type":"paragraph","inlineContent":[{"text":"Allow multiple payloads","type":"text"}]}],[{"type":"paragraph","inlineContent":[{"type":"text","text":"N/A"}]}]]],"header":"row","extendedData":{"0_1":{"colspan":0,"rowspan":1},"0_0":{"colspan":0,"rowspan":1}}},{"text":"Profile example","type":"heading","anchor":"Profile-example","level":3},{"type":"codeListing","syntax":"plist","code":["<?xml version=\"1.0\" encoding=\"UTF-8\"?>","<!DOCTYPE plist PUBLIC \"-//Apple//DTD PLIST 1.0//EN\" \"http://www.apple.com/DTDs/PropertyList-1.0.dtd\">","<plist version=\"1.0\">","<dict>","    <key>PayloadContent</key>","    <array>","        <dict>","            <key>tilesize</key>","            <integer>40</integer>","            <key>size-immutable</key>","            <true/>","            <key>magnification</key>","            <true/>","            <key>magnify-immutable</key>","            <true/>","            <key>largesize</key>","            <integer>100</integer>","            <key>magsize-immutable</key>","            <true/>","            <key>orientation</key>","            <string>left</string>","            <key>position-immutable</key>","            <true/>","            <key>mineffect</key>","            <string>genie</string>","            <key>mineffect-immutable</key>","            <true/>","            <key>windowtabbing</key>","            <string>manual</string>","            <key>windowtabbing-immutable</key>","            <true/>","            <key>dblclickbehavior</key>","            <string>maximize</string>","            <key>dblclickbehavior-immutable</key>","            <true/>","            <key>minimize-to-application</key>","            <true/>","            <key>minintoapp-immutable</key>","            <true/>","            <key>launchanim</key>","            <true/>","            <key>launchanim-immutable</key>","            <true/>","            <key>autohide</key>","            <false/>","            <key>autohide-immutable</key>","            <true/>","            <key>show-process-indicators</key>","            <false/>","            <key>showindicators-immutable</key>","            <true/>","            <key>show-recents</key>","            <false/>","            <key>showrecents-immutable</key>","            <true/>","            <key>PayloadIdentifier</key>","            <string>com.example.mydockpayload</string>","            <key>PayloadType</key>","            <string>com.apple.dock</string>","            <key>PayloadUUID</key>","            <string>8d443602-52f2-48ff-aaa9-35b16c7c54c9</string>","            <key>PayloadVersion</key>","            <integer>1</integer>","        </dict>","    </array>","    <key>PayloadDisplayName</key>","    <string>Dock</string>","    <key>PayloadIdentifier</key>","    <string>com.example.myprofile</string>","    <key>PayloadType</key>","    <string>Configuration</string>","    <key>PayloadUUID</key>","    <string>c139d3e0-5468-43b0-90bf-5e05b2e8cd6f</string>","    <key>PayloadVersion</key>","    <integer>1</integer>","</dict>","</plist>"]}],"kind":"content"}],"metadata":{"fragments":[{"kind":"text","text":"object "},{"text":"Dock","kind":"identifier"}],"externalID":"mdm-profiles:Dock","platforms":[{"beta":false,"introducedAt":"10.7","name":"macOS"}],"roleHeading":"Device Management Profile","symbolKind":"dictionary","navigatorTitle":[{"kind":"identifier","text":"Dock"}],"title":"Dock","role":"symbol","modules":[{"name":"Device Management"}]},"variants":[{"traits":[{"interfaceLanguage":"data"}],"paths":["/documentation/devicemanagement/dock"]}],"sections":[],"kind":"symbol","identifier":{"interfaceLanguage":"data","url":"doc://com.apple.devicemanagement/documentation/DeviceManagement/Dock"},"references":{"doc://com.apple.devicemanagement/documentation/DeviceManagement/TimeMachine":{"role":"symbol","fragments":[{"kind":"text","text":"object "},{"text":"TimeMachine","kind":"identifier"}],"title":"TimeMachine","abstract":[{"type":"text","text":"The payload that configures Time Machine."}],"navigatorTitle":[{"text":"TimeMachine","kind":"identifier"}],"url":"/documentation/devicemanagement/timemachine","identifier":"doc://com.apple.devicemanagement/documentation/DeviceManagement/TimeMachine","kind":"symbol","type":"topic"},"doc://com.apple.devicemanagement/documentation/DeviceManagement/SetupAssistant":{"title":"SetupAssistant","abstract":[{"text":"The payload that configures Setup Assistant settings.","type":"text"}],"url":"/documentation/devicemanagement/setupassistant","fragments":[{"kind":"text","text":"object "},{"text":"SetupAssistant","kind":"identifier"}],"type":"topic","navigatorTitle":[{"kind":"identifier","text":"SetupAssistant"}],"role":"symbol","kind":"symbol","identifier":"doc://com.apple.devicemanagement/documentation/DeviceManagement/SetupAssistant"},"doc://com.apple.devicemanagement/documentation/DeviceManagement/Finder":{"type":"topic","abstract":[{"text":"The payload that configures Finder settings.","type":"text"}],"role":"symbol","url":"/documentation/devicemanagement/finder","fragments":[{"text":"object ","kind":"text"},{"text":"Finder","kind":"identifier"}],"kind":"symbol","title":"Finder","identifier":"doc://com.apple.devicemanagement/documentation/DeviceManagement/Finder","navigatorTitle":[{"text":"Finder","kind":"identifier"}]},"doc://com.apple.documentation/documentation/technologies":{"identifier":"doc://com.apple.documentation/documentation/technologies","abstract":[{"text":"","type":"text"}],"kind":"technologies","url":"/documentation/technologies","role":"overview","title":"Technologies","type":"topic"},"doc://com.apple.devicemanagement/documentation/DeviceManagement/HomeScreenLayout":{"type":"topic","navigatorTitle":[{"text":"HomeScreenLayout","kind":"identifier"}],"role":"symbol","url":"/documentation/devicemanagement/homescreenlayout","fragments":[{"kind":"text","text":"object "},{"kind":"identifier","text":"HomeScreenLayout"}],"identifier":"doc://com.apple.devicemanagement/documentation/DeviceManagement/HomeScreenLayout","kind":"symbol","title":"HomeScreenLayout","abstract":[{"type":"text","text":"The payload that configures the Home Screen layout."}]},"doc://com.apple.devicemanagement/documentation/DeviceManagement/ScreensaverUser":{"navigatorTitle":[{"kind":"identifier","text":"ScreensaverUser"}],"title":"ScreensaverUser","kind":"symbol","role":"symbol","fragments":[{"kind":"text","text":"object "},{"text":"ScreensaverUser","kind":"identifier"}],"abstract":[{"text":"The payload that configures a user’s screen saver settings.","type":"text"}],"url":"/documentation/devicemanagement/screensaveruser","type":"topic","identifier":"doc://com.apple.devicemanagement/documentation/DeviceManagement/ScreensaverUser"},"doc://com.apple.devicemanagement/documentation/DeviceManagement/Desktop":{"identifier":"doc://com.apple.devicemanagement/documentation/DeviceManagement/Desktop","abstract":[{"type":"text","text":"The payload that configures the desktop wallpaper."}],"fragments":[{"text":"object ","kind":"text"},{"kind":"identifier","text":"Desktop"}],"navigatorTitle":[{"text":"Desktop","kind":"identifier"}],"title":"Desktop","type":"topic","url":"/documentation/devicemanagement/desktop","kind":"symbol","role":"symbol"},"doc://com.apple.devicemanagement/documentation/DeviceManagement/ManagedMenuExtras":{"fragments":[{"kind":"text","text":"object "},{"text":"ManagedMenuExtras","kind":"identifier"}],"role":"symbol","identifier":"doc://com.apple.devicemanagement/documentation/DeviceManagement/ManagedMenuExtras","navigatorTitle":[{"kind":"identifier","text":"ManagedMenuExtras"}],"kind":"symbol","title":"ManagedMenuExtras","url":"/documentation/devicemanagement/managedmenuextras","type":"topic","abstract":[{"type":"text","text":"The payload that configures menu extras."}]},"doc://com.apple.devicemanagement/documentation/DeviceManagement/Dock":{"role":"symbol","url":"/documentation/devicemanagement/dock","navigatorTitle":[{"kind":"identifier","text":"Dock"}],"title":"Dock","type":"topic","kind":"symbol","abstract":[{"text":"The payload that configures the Dock.","type":"text"}],"fragments":[{"text":"object ","kind":"text"},{"text":"Dock","kind":"identifier"}],"identifier":"doc://com.apple.devicemanagement/documentation/DeviceManagement/Dock"},"doc://com.apple.devicemanagement/documentation/DeviceManagement/Accessibility":{"navigatorTitle":[{"text":"Accessibility","kind":"identifier"}],"abstract":[{"text":"The payload that configures the accessibility features of the device.","type":"text"}],"role":"symbol","url":"/documentation/devicemanagement/accessibility","fragments":[{"kind":"text","text":"object "},{"text":"Accessibility","kind":"identifier"}],"type":"topic","identifier":"doc://com.apple.devicemanagement/documentation/DeviceManagement/Accessibility","title":"Accessibility","kind":"symbol"},"doc://com.apple.devicemanagement/documentation/DeviceManagement/Notifications":{"title":"Notifications","identifier":"doc://com.apple.devicemanagement/documentation/DeviceManagement/Notifications","fragments":[{"text":"object ","kind":"text"},{"text":"Notifications","kind":"identifier"}],"abstract":[{"text":"The payload that configures notifications.","type":"text"}],"type":"topic","navigatorTitle":[{"text":"Notifications","kind":"identifier"}],"url":"/documentation/devicemanagement/notifications","kind":"symbol","role":"symbol"},"doc://com.apple.devicemanagement/documentation/DeviceManagement/Dock/StaticItem":{"title":"Dock.StaticItem","fragments":[{"kind":"text","text":"object "},{"kind":"identifier","text":"Dock.StaticItem"}],"kind":"symbol","url":"/documentation/devicemanagement/dock/staticitem","navigatorTitle":[{"text":"Dock.StaticItem","kind":"identifier"}],"identifier":"doc://com.apple.devicemanagement/documentation/DeviceManagement/Dock/StaticItem","role":"symbol","type":"topic","abstract":[{"type":"text","text":"Items that are located on the Documents side of the Dock and cannot be removed from that location."}]},"doc://com.apple.devicemanagement/documentation/DeviceManagement":{"title":"Device Management","url":"/documentation/devicemanagement","role":"collection","abstract":[{"text":"Manage your organization’s devices remotely.","type":"text"}],"identifier":"doc://com.apple.devicemanagement/documentation/DeviceManagement","type":"topic","kind":"symbol","navigatorTitle":[{"text":"Device Management","kind":"text"}]}},"legalNotices":{"copyright":"Copyright &copy; 2026 Apple Inc. All rights reserved.","termsOfUse":"https://www.apple.com/legal/internet-services/terms/site.html","privacyPolicy":"https://www.apple.com/privacy/privacy-policy"}}