{"primaryContentSections":[{"kind":"declarations","declarations":[{"tokens":[{"kind":"text","text":"object "},{"kind":"identifier","text":"ManagedMenuExtras"}],"platforms":["macOS"],"languages":["data"]}]},{"items":[{"attributes":[],"content":[{"type":"paragraph","inlineContent":[{"type":"text","text":"If "},{"code":"true","type":"codeVoice"},{"type":"text","text":", enables the AirPort menu extra."}]}],"introducedVersion":"10.7.0","name":"AirPort.menu","type":[{"kind":"text","text":"boolean"}],"required":false},{"attributes":[],"content":[{"inlineContent":[{"text":"If ","type":"text"},{"code":"true","type":"codeVoice"},{"text":", enables the Battery menu extra.","type":"text"}],"type":"paragraph"}],"introducedVersion":"10.7.0","name":"Battery.menu","type":[{"kind":"text","text":"boolean"}],"required":false},{"attributes":[],"content":[{"inlineContent":[{"type":"text","text":"If "},{"code":"true","type":"codeVoice"},{"type":"text","text":", enables the Bluetooth menu extra."}],"type":"paragraph"}],"introducedVersion":"10.7.0","name":"Bluetooth.menu","type":[{"kind":"text","text":"boolean"}],"required":false},{"attributes":[],"content":[{"inlineContent":[{"text":"If ","type":"text"},{"type":"codeVoice","code":"true"},{"text":", enables the Clock menu extra.","type":"text"}],"type":"paragraph"}],"introducedVersion":"10.7.0","name":"Clock.menu","type":[{"text":"boolean","kind":"text"}],"required":false},{"attributes":[],"content":[{"inlineContent":[{"type":"text","text":"If "},{"type":"codeVoice","code":"true"},{"type":"text","text":", enables the CPU menu extra."}],"type":"paragraph"}],"introducedVersion":"10.7.0","name":"CPU.menu","type":[{"kind":"text","text":"boolean"}],"required":false},{"attributes":[{"value":"2.5","kind":"default"}],"content":[{"inlineContent":[{"text":"The number of seconds to delay after login before adding or removing menu extras. If the delay is too short, the menu extras don’t appear, or disappear from the menu bar.","type":"text"}],"type":"paragraph"}],"introducedVersion":"10.7.0","name":"delaySeconds","type":[{"kind":"text","text":"number"}],"required":false},{"attributes":[],"content":[{"inlineContent":[{"text":"If ","type":"text"},{"type":"codeVoice","code":"true"},{"text":", enables the Displays menu extra.","type":"text"}],"type":"paragraph"}],"introducedVersion":"10.7.0","name":"Displays.menu","type":[{"kind":"text","text":"boolean"}],"required":false},{"attributes":[],"content":[{"type":"paragraph","inlineContent":[{"text":"If ","type":"text"},{"code":"true","type":"codeVoice"},{"text":", enables the Eject menu extra.","type":"text"}]}],"introducedVersion":"10.7.0","name":"Eject.menu","type":[{"text":"boolean","kind":"text"}],"required":false},{"attributes":[],"content":[{"inlineContent":[{"text":"If ","type":"text"},{"code":"true","type":"codeVoice"},{"text":", enables the Fax menu extra.","type":"text"}],"type":"paragraph"}],"introducedVersion":"10.7.0","name":"Fax.menu","type":[{"kind":"text","text":"boolean"}],"required":false},{"attributes":[],"content":[{"type":"paragraph","inlineContent":[{"text":"If ","type":"text"},{"code":"true","type":"codeVoice"},{"text":", enables the HomeSync menu extra.","type":"text"}]}],"introducedVersion":"10.7.0","name":"HomeSync.menu","type":[{"text":"boolean","kind":"text"}],"required":false},{"attributes":[],"content":[{"type":"paragraph","inlineContent":[{"text":"If ","type":"text"},{"code":"true","type":"codeVoice"},{"text":", enables the iChat menu extra.","type":"text"}]}],"introducedVersion":"10.7.0","name":"iChat.menu","type":[{"kind":"text","text":"boolean"}],"required":false},{"attributes":[],"content":[{"type":"paragraph","inlineContent":[{"text":"If ","type":"text"},{"code":"true","type":"codeVoice"},{"text":", enables the Ink menu extra.","type":"text"}]}],"introducedVersion":"10.7.0","name":"Ink.menu","type":[{"kind":"text","text":"boolean"}],"required":false},{"attributes":[],"content":[{"type":"paragraph","inlineContent":[{"text":"If ","type":"text"},{"code":"true","type":"codeVoice"},{"text":", enables the IrDA menu extra.","type":"text"}]}],"introducedVersion":"10.7.0","name":"IrDA.menu","type":[{"text":"boolean","kind":"text"}],"required":false},{"attributes":[{"kind":"default","value":"20"}],"content":[{"type":"paragraph","inlineContent":[{"type":"text","text":"The maximum wait, in seconds, for all menu extras to be added or removed."}]}],"introducedVersion":"10.7.0","name":"maxWaitSeconds","type":[{"kind":"text","text":"number"}],"required":false},{"attributes":[],"content":[{"inlineContent":[{"type":"text","text":"If "},{"type":"codeVoice","code":"true"},{"type":"text","text":", enables the PCCard menu extra."}],"type":"paragraph"}],"introducedVersion":"10.7.0","name":"PCCard.menu","type":[{"kind":"text","text":"boolean"}],"required":false},{"attributes":[],"content":[{"inlineContent":[{"type":"text","text":"If "},{"code":"true","type":"codeVoice"},{"type":"text","text":", enables the PPP menu extra."}],"type":"paragraph"}],"introducedVersion":"10.7.0","name":"PPP.menu","type":[{"text":"boolean","kind":"text"}],"required":false},{"attributes":[],"content":[{"type":"paragraph","inlineContent":[{"text":"If ","type":"text"},{"type":"codeVoice","code":"true"},{"text":", enables the PPPoE menu extra.","type":"text"}]}],"introducedVersion":"10.7.0","name":"PPPoE.menu","type":[{"text":"boolean","kind":"text"}],"required":false},{"attributes":[],"content":[{"inlineContent":[{"type":"text","text":"If "},{"code":"true","type":"codeVoice"},{"type":"text","text":", enables the Remote Desktop menu extra."}],"type":"paragraph"}],"introducedVersion":"10.7.0","name":"RemoteDesktop.menu","type":[{"text":"boolean","kind":"text"}],"required":false},{"attributes":[],"content":[{"inlineContent":[{"text":"If ","type":"text"},{"type":"codeVoice","code":"true"},{"text":", enables the Script menu extra.","type":"text"}],"type":"paragraph"}],"introducedVersion":"10.7.0","name":"Script Menu.menu","type":[{"kind":"text","text":"boolean"}],"required":false},{"attributes":[],"content":[{"inlineContent":[{"text":"If ","type":"text"},{"code":"true","type":"codeVoice"},{"text":", enables the Spaces menu extra.","type":"text"}],"type":"paragraph"}],"introducedVersion":"10.7.0","name":"Spaces.menu","type":[{"text":"boolean","kind":"text"}],"required":false},{"attributes":[],"content":[{"type":"paragraph","inlineContent":[{"type":"text","text":"If "},{"type":"codeVoice","code":"true"},{"type":"text","text":", enables the Sync menu extra."}]}],"introducedVersion":"10.7.0","name":"Sync.menu","type":[{"text":"boolean","kind":"text"}],"required":false},{"attributes":[],"content":[{"inlineContent":[{"type":"text","text":"If "},{"type":"codeVoice","code":"true"},{"type":"text","text":", enables the Text Input menu extra."}],"type":"paragraph"}],"introducedVersion":"10.7.0","name":"TextInput.menu","type":[{"text":"boolean","kind":"text"}],"required":false},{"attributes":[],"content":[{"inlineContent":[{"text":"If ","type":"text"},{"code":"true","type":"codeVoice"},{"text":", enables the TimeMachine menu extra.","type":"text"}],"type":"paragraph"}],"introducedVersion":"10.7.0","name":"TimeMachine.menu","type":[{"text":"boolean","kind":"text"}],"required":false},{"attributes":[],"content":[{"inlineContent":[{"type":"text","text":"If "},{"type":"codeVoice","code":"true"},{"type":"text","text":", enables the Universal Access menu extra."}],"type":"paragraph"}],"introducedVersion":"10.7.0","name":"UniversalAccess.menu","type":[{"text":"boolean","kind":"text"}],"required":false},{"attributes":[],"content":[{"type":"paragraph","inlineContent":[{"type":"text","text":"If "},{"code":"true","type":"codeVoice"},{"type":"text","text":", enables the User menu extra."}]}],"introducedVersion":"10.7.0","name":"User.menu","type":[{"text":"boolean","kind":"text"}],"required":false},{"attributes":[],"content":[{"inlineContent":[{"type":"text","text":"If "},{"type":"codeVoice","code":"true"},{"type":"text","text":", enables the Volume menu extra."}],"type":"paragraph"}],"introducedVersion":"10.7.0","name":"Volume.menu","type":[{"text":"boolean","kind":"text"}],"required":false},{"attributes":[],"content":[{"type":"paragraph","inlineContent":[{"text":"If ","type":"text"},{"code":"true","type":"codeVoice"},{"text":", enables the VPN menu extra.","type":"text"}]}],"introducedVersion":"10.7.0","name":"VPN.menu","type":[{"text":"boolean","kind":"text"}],"required":false},{"attributes":[],"content":[{"type":"paragraph","inlineContent":[{"text":"If ","type":"text"},{"code":"true","type":"codeVoice"},{"text":", enables the WWAN menu extra.","type":"text"}]}],"introducedVersion":"10.7.0","name":"WWAN.menu","type":[{"text":"boolean","kind":"text"}],"required":false}],"title":"Properties","kind":"properties"},{"content":[{"text":"Discussion","type":"heading","anchor":"Discussion","level":2},{"type":"paragraph","inlineContent":[{"text":"Specify ","type":"text"},{"code":"com.apple.mcxMenuExtras","type":"codeVoice"},{"text":" as the payload type.","type":"text"}]},{"text":"Profile availability","type":"heading","anchor":"Profile-availability","level":3},{"extendedData":{"0_1":{"rowspan":1,"colspan":0},"0_0":{"colspan":0,"rowspan":1}},"rows":[[[{"inlineContent":[],"type":"paragraph"}],[{"inlineContent":[],"type":"paragraph"}]],[[{"inlineContent":[{"type":"text","text":"Device channel"}],"type":"paragraph"}],[{"inlineContent":[{"type":"text","text":"macOS"}],"type":"paragraph"}]],[[{"inlineContent":[{"type":"text","text":"User channel"}],"type":"paragraph"}],[{"inlineContent":[{"text":"macOS","type":"text"}],"type":"paragraph"}]],[[{"inlineContent":[{"type":"text","text":"Allow manual install"}],"type":"paragraph"}],[{"inlineContent":[{"type":"text","text":"macOS"}],"type":"paragraph"}]],[[{"inlineContent":[{"type":"text","text":"Requires supervision"}],"type":"paragraph"}],[{"inlineContent":[{"text":"NA","type":"text"}],"type":"paragraph"}]],[[{"inlineContent":[{"type":"text","text":"Requires user-approved MDM"}],"type":"paragraph"}],[{"inlineContent":[{"type":"text","text":"NA"}],"type":"paragraph"}]],[[{"inlineContent":[{"type":"text","text":"Allowed in user enrollment"}],"type":"paragraph"}],[{"inlineContent":[{"type":"text","text":"NA"}],"type":"paragraph"}]],[[{"inlineContent":[{"text":"Allow multiple payloads","type":"text"}],"type":"paragraph"}],[{"inlineContent":[{"text":"NA","type":"text"}],"type":"paragraph"}]]],"type":"table","header":"row"},{"text":"Profile example","type":"heading","anchor":"Profile-example","level":3},{"syntax":"plist","type":"codeListing","code":["<?xml version=\"1.0\" encoding=\"UTF-8\"?>","<!DOCTYPE plist PUBLIC \"-//Apple//DTD PLIST 1.0//EN\" \"http://www.apple.com/DTDs/PropertyList-1.0.dtd\">","<plist version=\"1.0\">","<dict>","    <key>PayloadContent</key>","    <array>","        <dict>","            <key>Battery.menu</key>","            <false/>","            <key>delaySeconds</key>","            <integer>30</integer>","            <key>maxWaitSeconds</key>","            <integer>60</integer>","            <key>PayloadIdentifier</key>","            <string>com.example.mymanagedmenuextraspayload</string>","            <key>PayloadType</key>","            <string>com.apple.mcxMenuExtras</string>","            <key>PayloadUUID</key>","            <string>93bd5b68-0141-4055-aaaf-a6cebc1cfeeb</string>","            <key>PayloadVersion</key>","            <integer>1</integer>","        </dict>","    </array>","    <key>PayloadDisplayName</key>","    <string>Menu Extras</string>","    <key>PayloadIdentifier</key>","    <string>com.example.myprofile</string>","    <key>PayloadType</key>","    <string>Configuration</string>","    <key>PayloadUUID</key>","    <string>dc2618ce-736c-4af7-b652-f9cdf3eb9ce4</string>","    <key>PayloadVersion</key>","    <integer>1</integer>","</dict>","</plist>"]}],"kind":"content"}],"metadata":{"platforms":[{"introducedAt":"10.7","beta":false,"name":"macOS"}],"externalID":"mdm-profiles:ManagedMenuExtras","title":"ManagedMenuExtras","symbolKind":"dictionary","fragments":[{"kind":"text","text":"object "},{"kind":"identifier","text":"ManagedMenuExtras"}],"roleHeading":"Device Management Profile","role":"symbol","modules":[{"name":"Device Management"}],"navigatorTitle":[{"kind":"identifier","text":"ManagedMenuExtras"}]},"schemaVersion":{"major":0,"minor":3,"patch":0},"identifier":{"interfaceLanguage":"data","url":"doc://com.apple.devicemanagement/documentation/DeviceManagement/ManagedMenuExtras"},"seeAlsoSections":[{"anchor":"User-Experience","title":"User Experience","identifiers":["doc://com.apple.devicemanagement/documentation/DeviceManagement/Accessibility","doc://com.apple.devicemanagement/documentation/DeviceManagement/Desktop","doc://com.apple.devicemanagement/documentation/DeviceManagement/Dock","doc://com.apple.devicemanagement/documentation/DeviceManagement/Finder","doc://com.apple.devicemanagement/documentation/DeviceManagement/HomeScreenLayout","doc://com.apple.devicemanagement/documentation/DeviceManagement/Notifications","doc://com.apple.devicemanagement/documentation/DeviceManagement/ScreensaverUser","doc://com.apple.devicemanagement/documentation/DeviceManagement/SetupAssistant","doc://com.apple.devicemanagement/documentation/DeviceManagement/TimeMachine"],"generated":true}],"sections":[],"kind":"symbol","variants":[{"paths":["/documentation/devicemanagement/managedmenuextras"],"traits":[{"interfaceLanguage":"data"}]}],"hierarchy":{"paths":[["doc://com.apple.documentation/documentation/technologies","doc://com.apple.devicemanagement/documentation/DeviceManagement"]]},"abstract":[{"text":"The payload that configures menu extras.","type":"text"}],"references":{"doc://com.apple.devicemanagement/documentation/DeviceManagement/TimeMachine":{"title":"TimeMachine","abstract":[{"text":"The payload that configures Time Machine.","type":"text"}],"kind":"symbol","navigatorTitle":[{"kind":"identifier","text":"TimeMachine"}],"url":"/documentation/devicemanagement/timemachine","identifier":"doc://com.apple.devicemanagement/documentation/DeviceManagement/TimeMachine","role":"symbol","type":"topic","fragments":[{"text":"object ","kind":"text"},{"text":"TimeMachine","kind":"identifier"}]},"doc://com.apple.devicemanagement/documentation/DeviceManagement/Desktop":{"type":"topic","identifier":"doc://com.apple.devicemanagement/documentation/DeviceManagement/Desktop","navigatorTitle":[{"text":"Desktop","kind":"identifier"}],"fragments":[{"kind":"text","text":"object "},{"kind":"identifier","text":"Desktop"}],"title":"Desktop","abstract":[{"text":"The payload that configures the desktop wallpaper.","type":"text"}],"role":"symbol","kind":"symbol","url":"/documentation/devicemanagement/desktop"},"doc://com.apple.devicemanagement/documentation/DeviceManagement/Dock":{"url":"/documentation/devicemanagement/dock","kind":"symbol","abstract":[{"type":"text","text":"The payload that configures the Dock."}],"role":"symbol","fragments":[{"text":"object ","kind":"text"},{"text":"Dock","kind":"identifier"}],"type":"topic","identifier":"doc://com.apple.devicemanagement/documentation/DeviceManagement/Dock","navigatorTitle":[{"text":"Dock","kind":"identifier"}],"title":"Dock"},"doc://com.apple.documentation/documentation/technologies":{"kind":"technologies","url":"/documentation/technologies","title":"Technologies","role":"overview","identifier":"doc://com.apple.documentation/documentation/technologies","abstract":[{"text":"","type":"text"}],"type":"topic"},"doc://com.apple.devicemanagement/documentation/DeviceManagement":{"kind":"symbol","url":"/documentation/devicemanagement","title":"Device Management","role":"collection","identifier":"doc://com.apple.devicemanagement/documentation/DeviceManagement","abstract":[{"text":"Manage your organization’s devices remotely.","type":"text"}],"type":"topic"},"doc://com.apple.devicemanagement/documentation/DeviceManagement/HomeScreenLayout":{"role":"symbol","abstract":[{"text":"The payload that configures the Home Screen layout.","type":"text"}],"type":"topic","navigatorTitle":[{"text":"HomeScreenLayout","kind":"identifier"}],"title":"HomeScreenLayout","kind":"symbol","fragments":[{"kind":"text","text":"object "},{"text":"HomeScreenLayout","kind":"identifier"}],"identifier":"doc://com.apple.devicemanagement/documentation/DeviceManagement/HomeScreenLayout","url":"/documentation/devicemanagement/homescreenlayout"},"doc://com.apple.devicemanagement/documentation/DeviceManagement/ScreensaverUser":{"fragments":[{"text":"object ","kind":"text"},{"text":"ScreensaverUser","kind":"identifier"}],"navigatorTitle":[{"text":"ScreensaverUser","kind":"identifier"}],"url":"/documentation/devicemanagement/screensaveruser","identifier":"doc://com.apple.devicemanagement/documentation/DeviceManagement/ScreensaverUser","abstract":[{"text":"The payload that configures a user’s screen saver settings.","type":"text"}],"kind":"symbol","title":"ScreensaverUser","role":"symbol","type":"topic"},"doc://com.apple.devicemanagement/documentation/DeviceManagement/ManagedMenuExtras":{"abstract":[{"text":"The payload that configures menu extras.","type":"text"}],"identifier":"doc://com.apple.devicemanagement/documentation/DeviceManagement/ManagedMenuExtras","type":"topic","title":"ManagedMenuExtras","navigatorTitle":[{"text":"ManagedMenuExtras","kind":"identifier"}],"role":"symbol","fragments":[{"text":"object ","kind":"text"},{"text":"ManagedMenuExtras","kind":"identifier"}],"kind":"symbol","url":"/documentation/devicemanagement/managedmenuextras"},"doc://com.apple.devicemanagement/documentation/DeviceManagement/SetupAssistant":{"fragments":[{"kind":"text","text":"object "},{"kind":"identifier","text":"SetupAssistant"}],"title":"SetupAssistant","abstract":[{"text":"The payload that configures Setup Assistant settings.","type":"text"}],"identifier":"doc://com.apple.devicemanagement/documentation/DeviceManagement/SetupAssistant","kind":"symbol","url":"/documentation/devicemanagement/setupassistant","role":"symbol","navigatorTitle":[{"kind":"identifier","text":"SetupAssistant"}],"type":"topic"},"doc://com.apple.devicemanagement/documentation/DeviceManagement/Finder":{"url":"/documentation/devicemanagement/finder","kind":"symbol","abstract":[{"text":"The payload that configures Finder settings.","type":"text"}],"role":"symbol","fragments":[{"text":"object ","kind":"text"},{"text":"Finder","kind":"identifier"}],"type":"topic","identifier":"doc://com.apple.devicemanagement/documentation/DeviceManagement/Finder","navigatorTitle":[{"text":"Finder","kind":"identifier"}],"title":"Finder"},"doc://com.apple.devicemanagement/documentation/DeviceManagement/Notifications":{"abstract":[{"text":"The payload that configures notifications.","type":"text"}],"identifier":"doc://com.apple.devicemanagement/documentation/DeviceManagement/Notifications","type":"topic","title":"Notifications","navigatorTitle":[{"text":"Notifications","kind":"identifier"}],"role":"symbol","fragments":[{"text":"object ","kind":"text"},{"text":"Notifications","kind":"identifier"}],"kind":"symbol","url":"/documentation/devicemanagement/notifications"},"doc://com.apple.devicemanagement/documentation/DeviceManagement/Accessibility":{"fragments":[{"kind":"text","text":"object "},{"kind":"identifier","text":"Accessibility"}],"title":"Accessibility","abstract":[{"type":"text","text":"The payload that configures the accessibility features of the device."}],"identifier":"doc://com.apple.devicemanagement/documentation/DeviceManagement/Accessibility","kind":"symbol","url":"/documentation/devicemanagement/accessibility","role":"symbol","navigatorTitle":[{"kind":"identifier","text":"Accessibility"}],"type":"topic"}},"legalNotices":{"copyright":"Copyright &copy; 2025 Apple Inc. All rights reserved.","termsOfUse":"https://www.apple.com/legal/internet-services/terms/site.html","privacyPolicy":"https://www.apple.com/privacy/privacy-policy"}}